LICENSE
MANIFEST.in
NOTICE
README.md
pyproject.toml
src/pyNuMAD.egg-info/PKG-INFO
src/pyNuMAD.egg-info/SOURCES.txt
src/pyNuMAD.egg-info/dependency_links.txt
src/pyNuMAD.egg-info/requires.txt
src/pyNuMAD.egg-info/top_level.txt
src/pynumad/__init__.py
src/pynumad/paths.py
src/pynumad/software_paths.json
src/pynumad/analysis/__init__.py
src/pynumad/analysis/beam_utils.py
src/pynumad/analysis/make_models.py
src/pynumad/analysis/abaqus/read.py
src/pynumad/analysis/abaqus/write.py
src/pynumad/analysis/ansys/main_ansys_analysis.py
src/pynumad/analysis/ansys/read.py
src/pynumad/analysis/ansys/run.py
src/pynumad/analysis/ansys/utility.py
src/pynumad/analysis/ansys/write.py
src/pynumad/analysis/cubit/__init__.py
src/pynumad/analysis/cubit/connect_cross_sections.py
src/pynumad/analysis/cubit/make_blade.py
src/pynumad/analysis/cubit/make_cross_sections.py
src/pynumad/data/__init__.py
src/pynumad/data/airfoils/DU91-W-250.txt
src/pynumad/data/airfoils/DU93-W-210.txt
src/pynumad/data/airfoils/DU97-W-300.txt
src/pynumad/data/airfoils/DU99-W-350.txt
src/pynumad/data/airfoils/DU99-W-405.txt
src/pynumad/data/airfoils/NACA-63-214.txt
src/pynumad/data/airfoils/NACA-64-618.txt
src/pynumad/data/airfoils/circular.txt
src/pynumad/data/blade_yamls/BAR0_NREL_1_4_2021.yaml
src/pynumad/data/blade_yamls/BAR1_SNL_1_18_2021.yaml
src/pynumad/data/blade_yamls/BAR2_HeavyTow_SNL_1_25_2021.yaml
src/pynumad/data/blade_yamls/BAR2_SNL_1_18_2021.yaml
src/pynumad/data/blade_yamls/BAR3_HeavyTow_SNL_1_25_2021.yaml
src/pynumad/data/blade_yamls/BAR3_SNL_1_18_2021.yaml
src/pynumad/data/blade_yamls/BAR4_HeavyTow_SNL_1_25_2021.yaml
src/pynumad/data/blade_yamls/BAR4_SNL_1_18_2021.yaml
src/pynumad/data/blade_yamls/myBlade.yaml
src/pynumad/data/blades/blade.xlsx
src/pynumad/data/blades/blade.yaml
src/pynumad/data/templates/mat_ori.py.template
src/pynumad/data/templates/sd.i.template
src/pynumad/data/templates/sm.i.template
src/pynumad/graphics/__init__.py
src/pynumad/graphics/graphics.py
src/pynumad/io/__init__.py
src/pynumad/io/airfoil_to_xml.py
src/pynumad/io/excel_to_blade.py
src/pynumad/io/mesh_to_yaml.py
src/pynumad/io/xml_to_airfoil.py
src/pynumad/io/yaml_to_blade.py
