Metadata-Version: 2.1
Name: pyNuMAD
Version: 1.0.0
Summary: Numerical Manufacturing and Design Tool
Author-email: Kirk Bonney <klbonne@sandia.gov>, Ernesto Camarena <ecamare@sandia.gov>, Evan Anderson <evaande@sandia.gov>
Maintainer-email: Kirk Bonney <klbonne@sandia.gov>, Ernesto Camarena <ecamare@sandia.gov>, Evan Anderson <evaande@sandia.gov>
Project-URL: Homepage, https://github.com/sandialabs/pynumad
Project-URL: Documentation, https://sandialabs.github.io/pyNuMAD/
Project-URL: Bug Tracker, https://github.com/sandialabs/pyNuMAD/issues
Project-URL: Changelog, https://sandialabs.github.io/pyNuMAD/release-notes.html
Classifier: License :: OSI Approved :: BSD License
Classifier: Programming Language :: Python :: 3 :: Only
Classifier: Programming Language :: Python :: 3.8
Classifier: Programming Language :: Python :: 3.9
Classifier: Programming Language :: Python :: 3.10
Classifier: Programming Language :: Python :: 3.11
Classifier: Programming Language :: Python :: 3.12
Requires-Python: >=3.8
License-File: LICENSE
License-File: NOTICE
Requires-Dist: numpy
Requires-Dist: scipy
Requires-Dist: pandas
Requires-Dist: matplotlib
Requires-Dist: pyyaml
Requires-Dist: plotly
Requires-Dist: openpyxl
